{
  "variants": {
    "snowy\u003dfalse": [
      {
        "model": "block/grass_normal"
      },
      {
        "model": "block/grass_normal",
        "y": 90
      },
      {
        "model": "block/grass_normal",
        "y": 180
      },
      {
        "model": "block/grass_normal",
        "y": 270
      },
      {
        "model": "block/grass_normal/0"
      },
      {
        "model": "block/grass_normal/0",
        "y": 90
      },
      {
        "model": "block/grass_normal/0",
        "y": 180
      },
      {
        "model": "block/grass_normal/0",
        "y": 270
      },
      {
        "model": "block/grass_normal/1"
      },
      {
        "model": "block/grass_normal/1",
        "y": 90
      },
      {
        "model": "block/grass_normal/1",
        "y": 180
      },
      {
        "model": "block/grass_normal/1",
        "y": 270
      },
      {
        "model": "block/grass_normal/2"
      },
      {
        "model": "block/grass_normal/2",
        "y": 90
      },
      {
        "model": "block/grass_normal/2",
        "y": 180
      },
      {
        "model": "block/grass_normal/2",
        "y": 270
      },
      {
        "model": "block/grass_normal/3"
      },
      {
        "model": "block/grass_normal/3",
        "y": 90
      },
      {
        "model": "block/grass_normal/3",
        "y": 180
      },
      {
        "model": "block/grass_normal/3",
        "y": 270
      },
      {
        "model": "block/grass_normal/4"
      },
      {
        "model": "block/grass_normal/4",
        "y": 90
      },
      {
        "model": "block/grass_normal/4",
        "y": 180
      },
      {
        "model": "block/grass_normal/4",
        "y": 270
      }
    ],
    "snowy\u003dtrue": {
      "model": "block/grass_snowed"
    }
  }
}
